qt_slurm/__init__.py
qt_slurm/parallel_slurm.py
qt_slurm-1.4.0.dist-info/METADATA
qt_slurm-1.4.0.dist-info/WHEEL
qt_slurm-1.4.0.dist-info/RECORD
