Metadata-Version: 2.3
Name: qt_slurm
Version: 1.4.0
Summary: Slurm integration package
Author-email: Dylan Kawashiri <dkawashiri@physics.ucla.edu>
Classifier: License :: OSI Approved :: MIT License
Classifier: Operating System :: OS Independent
Classifier: Programming Language :: Python :: 3
Requires-Python: >=3.8
